odoo/addons/l10n_it_appointment_code/README.rst
odoo/addons/l10n_it_appointment_code/__init__.py
odoo/addons/l10n_it_appointment_code/__manifest__.py
odoo/addons/l10n_it_appointment_code/hooks.py
odoo/addons/l10n_it_appointment_code/data/appointment_code_data.xml
odoo/addons/l10n_it_appointment_code/i18n/it.po
odoo/addons/l10n_it_appointment_code/i18n/l10n_it_appointment_code.pot
odoo/addons/l10n_it_appointment_code/migrations/14.0.1.0.0/pre-migrate.py
odoo/addons/l10n_it_appointment_code/models/__init__.py
odoo/addons/l10n_it_appointment_code/models/appointment_code.py
odoo/addons/l10n_it_appointment_code/readme/CONFIGURE.rst
odoo/addons/l10n_it_appointment_code/readme/CONTRIBUTORS.rst
odoo/addons/l10n_it_appointment_code/readme/DESCRIPTION.rst
odoo/addons/l10n_it_appointment_code/readme/USAGE.rst
odoo/addons/l10n_it_appointment_code/security/ir.model.access.csv
odoo/addons/l10n_it_appointment_code/static/description/icon.png
odoo/addons/l10n_it_appointment_code/static/description/index.html
odoo/addons/l10n_it_appointment_code/views/appointment_code_view.xml
odoo14_addon_l10n_it_appointment_code-14.0.1.0.1.dist-info/METADATA
odoo14_addon_l10n_it_appointment_code-14.0.1.0.1.dist-info/WHEEL
odoo14_addon_l10n_it_appointment_code-14.0.1.0.1.dist-info/top_level.txt
odoo14_addon_l10n_it_appointment_code-14.0.1.0.1.dist-info/RECORD
